{
    "name": "まくいーん",
    "description": "高知高専作成 小中学生向けmicrobit:maqueen用教材",
    "dependencies": {
        "core": "*",
        "radio": "*",
        "microphone": "*",
        "maqueen": "github:dfrobot/pxt-maqueen#v1.5.3"
    },
    "files": [
        "main.blocks",
        "main.ts",
        "README.md",
        "custom.ts"
    ],
    "testFiles": [
        "test.ts"
    ],
    "targetVersions": {
        "target": "3.1.47",
        "targetId": "microbit"
    },
    "supportedTargets": [
        "microbit"
    ],
    "preferredEditor": "blocksprj"
}
